ltou/__init__.py
ltou/__main__.py
ltou/cli.py
ltou/model.py
ltou/template/.github/workflows/tests.yml
ltou/template/__init__.py
ltou/template/cookiecutter.json
ltou/template/hooks/__init__.py
ltou/template/hooks/post_gen_project.py
ltou/template/hooks/pre_gen_project.py
ltou/template/{{cookiecutter.project_name}}/.dockerignore
ltou/template/{{cookiecutter.project_name}}/.drone.yml
ltou/template/{{cookiecutter.project_name}}/.env_sample
ltou/template/{{cookiecutter.project_name}}/.gitignore
ltou/template/{{cookiecutter.project_name}}/.jenkins.yaml
ltou/template/{{cookiecutter.project_name}}/README.md
ltou/template/{{cookiecutter.project_name}}/__init__.py
ltou/template/{{cookiecutter.project_name}}/alembic.ini
ltou/template/{{cookiecutter.project_name}}/app/.dockerignore
ltou/template/{{cookiecutter.project_name}}/app/.gitignore
ltou/template/{{cookiecutter.project_name}}/app/.gitlab-ci.yml
ltou/template/{{cookiecutter.project_name}}/app/__init__.py
ltou/template/{{cookiecutter.project_name}}/app/api/__init__.py
ltou/template/{{cookiecutter.project_name}}/app/api/deps.py
ltou/template/{{cookiecutter.project_name}}/app/api/endpoints/__init__.py
ltou/template/{{cookiecutter.project_name}}/app/api/endpoints/api.py
ltou/template/{{cookiecutter.project_name}}/app/cli/__init__.py
ltou/template/{{cookiecutter.project_name}}/app/core/__init__.py
ltou/template/{{cookiecutter.project_name}}/app/core/config.py
ltou/template/{{cookiecutter.project_name}}/app/core/security.py
ltou/template/{{cookiecutter.project_name}}/app/crud/__init__.py
ltou/template/{{cookiecutter.project_name}}/app/docker/.Dockerfile
ltou/template/{{cookiecutter.project_name}}/app/docker/dev.Dockerfile
ltou/template/{{cookiecutter.project_name}}/app/docker/docker-compose.yml
ltou/template/{{cookiecutter.project_name}}/app/docker/prod.Dockerfile
ltou/template/{{cookiecutter.project_name}}/app/docker/test.Dockerfile
ltou/template/{{cookiecutter.project_name}}/app/exceptions.py
ltou-0.1.1.dist-info/WHEEL
ltou-0.1.1.dist-info/entry_points.txt
ltou-0.1.1.dist-info/METADATA
ltou-0.1.1.dist-info/RECORD
