Metadata-Version: 2.1
Name: ltou
Version: 0.1.1
Summary: Like 'cargo new' cli creat fastapi project
Home-page: https://github.com/linpan/ltou.git
Keywords: FastAPI,Cookiecutter,cli,template
Author: hiro
Author-email: yidiyu0507s@163.com
Requires-Python: >=3.8,<4.0
Classifier: Programming Language :: Python :: 3
Classifier: Programming Language :: Python :: 3.8
Classifier: Programming Language :: Python :: 3.9
Classifier: Programming Language :: Python :: 3.10
Classifier: Programming Language :: Python :: 3.11
Requires-Dist: click (>=8.1.3,<9.0.0)
Requires-Dist: cookiecutter (>=1.7.3,<2.0.0)
Requires-Dist: pre-commit (>=3.0.4,<4.0.0)
Requires-Dist: prompt-toolkit (>=3.0.36,<4.0.0)
Requires-Dist: pydantic (>=1.10.5,<2.0.0)
Requires-Dist: simple-term-menu (>=1.5.2,<2.0.0)
Requires-Dist: termcolor (>=2.2.0,<3.0.0)
Project-URL: Repository, https://github.com/linpan/ltou.git
